{
  "project_info": {
    "project_number": "164909332735",
    "project_id": "sehealthyapp",
    "storage_bucket": "sehealthyapp.firebasestorage.app"
  },
  "client": [
    {
      "client_info": {
        "mobilesdk_app_id": "1:164909332735:android:69761b090933267fbd34ca",
        "android_client_info": {
          "package_name": "com.example.sehealthyapp"
        }
      },
      "oauth_client": [
        {
          "client_id": "164909332735-0c6ndvkd7b49k04148r216scj1ucrice.apps.googleusercontent.com",
          "client_type": 1,
          "android_info": {
            "package_name": "com.example.sehealthyapp",
            "certificate_hash": "49ba797512eef03f7a755f40ca296bf93744ad3a"
          }
        },
        {
          "client_id": "164909332735-pnvck4dqnin8tpast0a68mtc08ndl034.apps.googleusercontent.com",
          "client_type": 3
        }
      ],
      "api_key": [
        {
          "current_key": "AIzaSyC-UnJR7s7qf10OaOMzL9DO7oyLlc_cYT8"
        }
      ],
      "services": {
        "appinvite_service": {
          "other_platform_oauth_client": [
            {
              "client_id": "164909332735-pnvck4dqnin8tpast0a68mtc08ndl034.apps.googleusercontent.com",
              "client_type": 3
            },
            {
              "client_id": "164909332735-f2pma4oe6r1d9ss7bb975kh1tpo8vog1.apps.googleusercontent.com",
              "client_type": 2,
              "ios_info": {
                "bundle_id": "com.example.sehealthyapp"
              }
            }
          ]
        }
      }
    }
  ],
  "configuration_version": "1"
}